alt_file_utils/__init__.py
alt_file_utils/constants.py
alt_file_utils/core.py
alt_file_utils/exceptions.py
alt_file_utils/py.typed
alt_file_utils-0.1.0.dist-info/licenses/LICENSE
alt_file_utils-0.1.0.dist-info/METADATA
alt_file_utils-0.1.0.dist-info/WHEEL
alt_file_utils-0.1.0.dist-info/top_level.txt
alt_file_utils-0.1.0.dist-info/RECORD
