Metadata-Version: 2.4
Name: ALT-file-utils
Version: 0.1.0
Summary: Robust file I/O utilities with atomic writes, retries, and comprehensive error handling
Author-email: Avi Layani <alayani@redhat.com>
Maintainer-email: Avi Layani <alayani@redhat.com>
License: MIT
Project-URL: Homepage, https://github.com/Avilir/ALT-file-utils
Project-URL: Repository, https://github.com/Avilir/ALT-file-utils
Project-URL: Bug Tracker, https://github.com/Avilir/ALT-file-utils/issues
Keywords: file,io,atomic,write,utilities,yaml,json,toml
Classifier: Development Status :: 3 - Alpha
Classifier: Intended Audience :: Developers
Classifier: License :: OSI Approved :: MIT License
Classifier: Operating System :: OS Independent
Classifier: Programming Language :: Python :: 3
Classifier: Programming Language :: Python :: 3.8
Classifier: Programming Language :: Python :: 3.9
Classifier: Programming Language :: Python :: 3.10
Classifier: Programming Language :: Python :: 3.11
Classifier: Programming Language :: Python :: 3.12
Classifier: Topic :: Software Development :: Libraries :: Python Modules
Classifier: Topic :: System :: Filesystems
Classifier: Topic :: Utilities
Classifier: Typing :: Typed
Requires-Python: >=3.8
License-File: LICENSE
Requires-Dist: pyyaml>=5.4
Provides-Extra: toml
Requires-Dist: tomli>=1.2.0; python_version < "3.11" and extra == "toml"
Provides-Extra: dev
Requires-Dist: pytest>=7.0.0; extra == "dev"
Requires-Dist: pytest-cov>=4.0.0; extra == "dev"
Requires-Dist: pytest-mock>=3.10.0; extra == "dev"
Requires-Dist: mypy>=1.0.0; extra == "dev"
Requires-Dist: ruff>=0.1.0; extra == "dev"
Requires-Dist: black>=23.0.0; extra == "dev"
Requires-Dist: pre-commit>=3.0.0; extra == "dev"
Requires-Dist: build>=0.10.0; extra == "dev"
Requires-Dist: twine>=4.0.0; extra == "dev"
Requires-Dist: types-PyYAML>=6.0.0; extra == "dev"
Provides-Extra: all
Requires-Dist: tomli>=1.2.0; python_version < "3.11" and extra == "all"
Dynamic: license-file
